vault/__init__.py
vault/cache.py
vault/client.py
vault/datatype.py
vault/vault.py
pyvault_client-0.1.1.dist-info/METADATA
pyvault_client-0.1.1.dist-info/WHEEL
pyvault_client-0.1.1.dist-info/licenses/LICENSE
pyvault_client-0.1.1.dist-info/RECORD
