Metadata-Version: 2.4
Name: pyvault-client
Version: 0.1.1
Summary: Flexible data and file storage, retrieval and caching system for Python applications 
Project-URL: Homepage, https://github.com/djtech-dev/vault
Project-URL: Issues, https://github.com/djtech-dev/vault/issues
Author-email: djtech-dev <djtech.developer@gmail.com>
License-Expression: GPL-3.0-or-later
License-File: LICENSE
Classifier: Operating System :: OS Independent
Classifier: Programming Language :: Python :: 3
Requires-Python: >=3.9
